botoease/__init__.py
botoease/base_storage.py
botoease/ignore.py
botoease/local_storage.py
botoease/s3_storage.py
botoease/storage.py
botoease-0.2.3.dist-info/LICENSE
botoease-0.2.3.dist-info/METADATA
botoease-0.2.3.dist-info/WHEEL
botoease-0.2.3.dist-info/top_level.txt
botoease-0.2.3.dist-info/RECORD
