Metadata-Version: 2.1
Name: botoease
Version: 0.2.3
Summary: A simple Python library for easy AWS S3 & local file storage
Author: Bhuvan G S
License: MIT
Keywords: storage,aws,s3,upload,local storage
Classifier: Programming Language :: Python :: 3
Classifier: Operating System :: OS Independent
Classifier: License :: OSI Approved :: MIT License
Requires-Python: >=3.8
License-File: LICENSE
Requires-Dist: boto3
